AUTHORS
LICENSE
MANIFEST.in
README.rst
setup.py
src/SimpleIDML.egg-info/PKG-INFO
src/SimpleIDML.egg-info/SOURCES.txt
src/SimpleIDML.egg-info/dependency_links.txt
src/SimpleIDML.egg-info/requires.txt
src/SimpleIDML.egg-info/top_level.txt
src/scripts/simpleidml_create_package_from_dir.py
src/scripts/simpleidml_indesign_close_all_documents.py
src/scripts/simpleidml_indesign_save_as.py
src/simple_idml/__init__.py
src/simple_idml/commands.py
src/simple_idml/components.py
src/simple_idml/decorators.py
src/simple_idml/exceptions.py
src/simple_idml/extras.py
src/simple_idml/ftp.py
src/simple_idml/id_package.py
src/simple_idml/idml.py
src/simple_idml/test.py
src/simple_idml/utils.py
src/simple_idml/indesign/__init__.py
src/simple_idml/indesign/indesign.py
src/simple_idml/indesign/scripts/close_all_documents.jsx
src/simple_idml/indesign/scripts/export.jsx
src/simple_idml/indesign/scripts/list_profiles.jsx
src/simple_idml/indesign/scripts/package_to_print.jsx
src/simple_idml/indesign/scripts/save_as.jsx
src/simpleidml.egg-info/PKG-INFO
src/simpleidml.egg-info/SOURCES.txt
src/simpleidml.egg-info/dependency_links.txt
src/simpleidml.egg-info/requires.txt
src/simpleidml.egg-info/top_level.txt
tests/Makefile
tests/coveragerc
tests/runtests.py
tests/regressiontests/__init__.py
tests/regressiontests/components.py
tests/regressiontests/extras.py
tests/regressiontests/id_package.py
tests/regressiontests/idml.py
tests/regressiontests/indesign.py
tests/regressiontests/utils.py
tests/regressiontests/IDML/2articles-0photo.idml
tests/regressiontests/IDML/2articles-0photo.indd
tests/regressiontests/IDML/2articles-1photo-elts-same-layer.idml
tests/regressiontests/IDML/2articles-1photo-elts-same-layer.indd
tests/regressiontests/IDML/2articles-1photo.idml
tests/regressiontests/IDML/2articles-1photo.indd
tests/regressiontests/IDML/4-pages-layers-with-guides.idml
tests/regressiontests/IDML/4-pages-layers-with-guides.indd
tests/regressiontests/IDML/4-pages.idml
tests/regressiontests/IDML/4-pages.indd
tests/regressiontests/IDML/article-1photo-package.zip
tests/regressiontests/IDML/article-1photo-with-attributes.idml
tests/regressiontests/IDML/article-1photo-with-attributes.indd
tests/regressiontests/IDML/article-1photo.idml
tests/regressiontests/IDML/article-1photo.indd
tests/regressiontests/IDML/article-1photo_import-xml.idml
