Metadata-Version: 2.1
Name: simpleidml
Version: 1.3.0
Summary: A library to manipulate Adobe(r) IDML(r) files.
Home-page: https://github.com/Starou/SimpleIDML
Author: Stanislas Guerra
Author-email: stanislas.guerra@gmail.com
License: BSD Licence
Project-URL: Source Code, https://github.com/Starou/SimpleIDML
Project-URL: Issue Tracker, https://github.com/Starou/SimpleIDML/issues
Classifier: Environment :: Console
Classifier: Intended Audience :: Developers
Classifier: License :: OSI Approved :: BSD License
Classifier: Operating System :: OS Independent
Classifier: Programming Language :: Python
Classifier: Programming Language :: Python :: 3
Classifier: Programming Language :: Python :: 3.11
Classifier: Topic :: Multimedia :: Graphics
Classifier: Topic :: Printing
Classifier: Topic :: Software Development :: Libraries :: Python Modules
License-File: LICENSE
License-File: AUTHORS
